Workbook

Sheet Start
C2: Ultimate Berlin & Potsdam Family Trip Budget Planner & Itinerary Tracker
C3: Simple yet powerful planner to track all travel expenses and activities in one place. Optimize your family trip with smart budgeting and time management.
C5: How it works
B6: 1. | C6: Enter your travel dates and budget
B7: 2. | C7: Add planned activities with costs
B8: 3. | C8: Track actual expenses as you travel
B9: 4. | C9: Monitor budget vs. actual spending
B10: 5. | C10: Update itinerary with time slots
B11: 6. | C11: Check recommendations for family-friendly activities
B12: 7. | C12: Export final report after your trip
C14: Only fill in white cells – green columns calculate automatically.
C16: Go to sheet
C17: → Dashboard
C18: → Expenses
C19: → Itinerary
C20: → Dashboard-2
C22: Made by Haiktec · haiktec.tech

Sheet Dashboard
B2: Dashboard – Ultimate Berlin & Potsdam Family Trip Budget Planner & Itine
B4: Key figures
B5: Total Budget | C5: =SUMIF(Expenses!B2:B100,'Accommodation',Expenses!F2:F100)+SUMIF(Expenses!B2:B100,'Transportation',Expenses!F2:F100)+SUMIF(Expenses!B2:B100,'Attractions',Expenses!F2:F100)
B6: Actual Spending | C6: =SUM(Expenses!F2:F100)
B7: Remaining Budget | C7: =VLOOKUP('Total Budget','Dashboard-2'!A2:B10,2,FALSE)-VLOOKUP('Actual Spending','Dashboard-2'!A2:B10,2,FALSE)
B8: Activities Planned | C8: =COUNTA(Itinerary!C2:C100)
B9: Food Expenses | C9: =SUMIF(Expenses!B2:B100,'Food',Expenses!F2:F100)
B10: Average Daily Spend | C10: =VLOOKUP('Actual Spending','Dashboard-2'!A2:B10,2,FALSE)/7

Sheet Expenses
A1: Date | B1: Category | C1: Item | D1: Quantity | E1: Unit Price | F1: Total
A2: 46127 | B2: Transportation | C2: Airport Transfer | D2: 1 | E2: 45 | F2: =D2*E2
A3: 46128 | B3: Food | C3: Lunch at Museum | D3: 4 | E3: 12.5 | F3: =D3*E3
A4: 46128 | B4: Attractions | C4: Pergamon Museum Tickets | D4: 2 | E4: 19 | F4: =D4*E4
A5: 46129 | B5: Transportation | C5: Day Pass Public Transport | D5: 2 | E5: 24 | F5: =D5*E5
A6: 46129 | B6: Food | C6: Dinner | D6: 4 | E6: 32 | F6: =D6*E6
A7: 46130 | B7: Attractions | C7: Sanssouci Palace | D7: 4 | E7: 14.5 | F7: =D7*E7
A8: 46130 | B8: Shopping | C8: Souvenirs | D8: 1 | E8: 25 | F8: =D8*E8
A9: 46131 | B9: Transportation | C9: Taxi to Airport | D9: 1 | E9: 35 | F9: =D9*E9
F10: =IF(A10="","",D10*E10)
F11: =IF(A11="","",D11*E11)
F12: =IF(A12="","",D12*E12)
F13: =IF(A13="","",D13*E13)
F14: =IF(A14="","",D14*E14)
F15: =IF(A15="","",D15*E15)
F16: =IF(A16="","",D16*E16)
F17: =IF(A17="","",D17*E17)
F18: =IF(A18="","",D18*E18)
F19: =IF(A19="","",D19*E19)
F20: =IF(A20="","",D20*E20)
F21: =IF(A21="","",D21*E21)
... F109: =IF(A109="","",D109*E109)

Sheet Itinerary
A1: Date | B1: Time | C1: Activity | D1: Location | E1: Duration | F1: Notes
A2: 46127 | B2: 14:00 | C2: Arrival at Airport | D2: BER | E2: 2 | F2: Flight number XYZ
A3: 46127 | B3: 16:00 | C3: Check-in hotel | D3: Mitte | E3: 1 | F3: Family room booked
A4: 46128 | B4: 09:00 | C4: Pergamon Museum | D4: Museum Island | E4: 4 | F4: With audio guide
A5: 46128 | B5: 14:00 | C5: Lunch break | D5: Café im Hof | E5: 1 | F5: Child-friendly
A6: 46129 | B6: 10:00 | C6: Day trip to Potsdam | D6: Sanssouci | E6: 8 | F6: Train at 9:30
A7: 46130 | B7: 09:00 | C7: Tierpark Berlin | D7: Friedrichsfelde | E7: 6 | F7: Animals
A8: 46131 | B8: 11:00 | C8: Return flight | D8: BER | E8: 1 | F8: Check-out at 10

Sheet Dashboard-2
A1: Metric | B1: Value
