Workbook

Sheet Inicio
C2: Berlin & Potsdam Trip Planner: Budget & Itinerary for Solo Male Travelers
C3: Planifica tu viaje perfecto a Berlín y Potsdam con este completo organizador de presupuesto e itinerario - todo en una sola hoja de cálculo profesional
C5: Cómo funciona
B6: 1. | C6: Configura tus fechas de viaje y moneda base
B7: 2. | C7: Añade tus actividades principales en el itinerario
B8: 3. | C8: Registra todos los gastos según categorías
B9: 4. | C9: Usa las alertas para no exceder tu presupuesto
B10: 5. | C10: Consulta el dashboard para ajustar tus planes
B11: 6. | C11: Exporta información clave como PDF antes de viajar
C13: Rellene solo las celdas blancas: las columnas verdes se calculan solas.
C15: Ir a la hoja
C16: → Resumen
C17: → Itinerario
C18: → Gastos
C19: → Resumen-2
C21: Creado por Haiktec · haiktec.tech

Sheet Resumen
B2: Resumen – Berlin & Potsdam Trip Planner: Budget & Itinerary for Solo M
B4: Indicadores
B5: Total gastado | C5: =SUMIF('Gastos'!D2:D100,'Gastos'!E2:E100,TRUE)
B6: Restante vs presupuesto | C6: =B2-SUM('Gastos'!D2:D100)
B7: % del presupuesto usado | C7: =SUM('Gastos'!D2:D100)/B2
B8: Actividades planeadas | C8: =COUNTA('Itinerario'!C2:C100)
B9: Días con transporte público | C9: =COUNTIF('Itinerario'!F2:F100,"Metro")+COUNTIF('Itinerario'!F2:F100,"Tren")+COUNTIF('Itinerario'!F2:F100,"Autobus")

Sheet Itinerario
A1: Fecha | B1: Hora | C1: Actividad | D1: Lugar | E1: Tiempo Transporte (min) | F1: Transporte | G1: Notas
A2: 46127 | B2: =IF(ISBLANK(D2), "", IFERROR(TIMEVALUE(D2), "")) | C2: Visita Puerta de Brandenburgo | D2: Pariser Platz | E2: 0 | G2: Llegar temprano para fotos
A3: 46127 | B3: =IF(ISBLANK(D3), "", IFERROR(TIMEVALUE(D3), "")) | C3: Almuerzo - restaurante tipico | D3: Kreuzberg | E3: 25 | F3: Metro U6 | G3: Reservar mesa
A4: 46127 | B4: =IF(ISBLANK(D4), "", IFERROR(TIMEVALUE(D4), "")) | C4: Museo de Pérgamo | D4: Museumsinsel | E4: 15 | F4: Caminando | G4: Tour guiado a las 16:00
A5: 46128 | B5: =IF(ISBLANK(D5), "", IFERROR(TIMEVALUE(D5), "")) | C5: Excursion a Potsdam | D5: Palacio Sanssouci | E5: 45 | F5: Tren RE1 | G5: Comprar tickets con anticipacion
B6: =IF(A6="","",IF(ISBLANK(D6), "", IFERROR(TIMEVALUE(D6), "")))
B7: =IF(A7="","",IF(ISBLANK(D7), "", IFERROR(TIMEVALUE(D7), "")))
B8: =IF(A8="","",IF(ISBLANK(D8), "", IFERROR(TIMEVALUE(D8), "")))
B9: =IF(A9="","",IF(ISBLANK(D9), "", IFERROR(TIMEVALUE(D9), "")))
B10: =IF(A10="","",IF(ISBLANK(D10), "", IFERROR(TIMEVALUE(D10), "")))
B11: =IF(A11="","",IF(ISBLANK(D11), "", IFERROR(TIMEVALUE(D11), "")))
B12: =IF(A12="","",IF(ISBLANK(D12), "", IFERROR(TIMEVALUE(D12), "")))
B13: =IF(A13="","",IF(ISBLANK(D13), "", IFERROR(TIMEVALUE(D13), "")))
B14: =IF(A14="","",IF(ISBLANK(D14), "", IFERROR(TIMEVALUE(D14), "")))
B15: =IF(A15="","",IF(ISBLANK(D15), "", IFERROR(TIMEVALUE(D15), "")))
B16: =IF(A16="","",IF(ISBLANK(D16), "", IFERROR(TIMEVALUE(D16), "")))
B17: =IF(A17="","",IF(ISBLANK(D17), "", IFERROR(TIMEVALUE(D17), "")))
... B85: =IF(A85="","",IF(ISBLANK(D85), "", IFERROR(TIMEVALUE(D85), "")))

Sheet Gastos
A1: Fecha | B1: Concepto | C1: Categoria | D1: Cantidad (EUR) | E1: Pagado | F1: Metodo Pago | G1: Notas
A2: 46124 | B2: Vuelo a Berlín | C2: Transporte | D2: 185 | E2: =IF(OR(E2=TRUE,E2=FALSE),E2,FALSE) | F2: Tarjeta credito | G2: Vuelo Iberia 10:30
A3: 46124 | B3: Seguro de viaje | C3: Seguro | D3: 42.5 | E3: =IF(OR(E3=TRUE,E3=FALSE),E3,FALSE) | F3: PayPal
A4: 46127 | B4: Entrada Museo | C4: Cultura | D4: 14 | E4: =IF(OR(E4=TRUE,E4=FALSE),E4,FALSE) | F4: Efectivo | G4: Pagar en sitio
A5: 46127 | B5: Almuerzo | C5: Comida | D5: 18.75 | E5: =IF(OR(E5=TRUE,E5=FALSE),E5,FALSE) | F5: Tarjeta debito | G5: Restaurante Hofbräu
E6: =IF(A6="","",IF(OR(E6=TRUE,E6=FALSE),E6,FALSE))
E7: =IF(A7="","",IF(OR(E7=TRUE,E7=FALSE),E7,FALSE))
E8: =IF(A8="","",IF(OR(E8=TRUE,E8=FALSE),E8,FALSE))
E9: =IF(A9="","",IF(OR(E9=TRUE,E9=FALSE),E9,FALSE))
E10: =IF(A10="","",IF(OR(E10=TRUE,E10=FALSE),E10,FALSE))
E11: =IF(A11="","",IF(OR(E11=TRUE,E11=FALSE),E11,FALSE))
E12: =IF(A12="","",IF(OR(E12=TRUE,E12=FALSE),E12,FALSE))
E13: =IF(A13="","",IF(OR(E13=TRUE,E13=FALSE),E13,FALSE))
E14: =IF(A14="","",IF(OR(E14=TRUE,E14=FALSE),E14,FALSE))
E15: =IF(A15="","",IF(OR(E15=TRUE,E15=FALSE),E15,FALSE))
E16: =IF(A16="","",IF(OR(E16=TRUE,E16=FALSE),E16,FALSE))
E17: =IF(A17="","",IF(OR(E17=TRUE,E17=FALSE),E17,FALSE))
... E105: =IF(A105="","",IF(OR(E105=TRUE,E105=FALSE),E105,FALSE))

Sheet Resumen-2
A1: Item | B1: Valor
