Workbook

Sheet Inicio
C2: Gestor de Eventos y Finanzas para Asociaciones y Voluntarios
C3: Planifica eventos, controla gastos y optimiza recursos con esta herramienta todo en uno para asociaciones. Ideal para equipos con voluntarios y presupuestos ajustados.
C5: Cómo funciona
B6: 1. | C6: Registra socios y voluntarios en la hoja 'Miembros'
B7: 2. | C7: Planifica eventos en la hoja 'Eventos' con fechas y presupuesto
B8: 3. | C8: Registra gastos e ingresos en la hoja 'Finanzas'
B9: 4. | C9: Revisa automáticamente el estado en el dashboard
B10: 5. | C10: Exporta informes para reuniones de junta directiva
B11: 6. | C11: Actualiza periódicamente el estado de las cuentas
C13: Rellene solo las celdas blancas: las columnas verdes se calculan solas.
C15: Ir a la hoja
C16: → Resumen
C17: → Eventos
C18: → Finanzas
C19: → Miembros
C21: Creado por Haiktec · haiktec.tech

Sheet Resumen
B2: Resumen – Gestor de Eventos y Finanzas para Asociaciones y Voluntarios
B4: Indicadores
B5: Total Ingresos | C5: =SUMIF('Finanzas'!E2:E300,"Ingreso",'Finanzas'!D2:D300)
B6: Total Gastos | C6: =SUMIF('Finanzas'!E2:E300,"Gasto",'Finanzas'!D2:D300)*(-1)
B7: Balance Actual | C7: =KPI!A1+KPI!A2
B8: Próximo Evento | C8: =TEXT(MIN('Eventos'!A2:A30),"dd/mm/yyyy") & " - " & VLOOKUP(MIN('Eventos'!A2:A30),'Eventos'!A2:F30,2,FALSE)
B9: Socios Activos | C9: =COUNTIF('Miembros'!D2:D200,"Sí")
B10: Presupuesto Eventos | C10: =SUM('Eventos'!E2:E30)

Sheet Eventos
A1: Fecha | B1: Nombre | C1: Tipo | D1: Lugar | E1: Presupuesto | F1: Participantes
A2: 46096 | B2: Carrera Solidaria | C2: Recaudación | D2: Parque Central | E2: 500 | F2: 0
A3: 46134 | B3: Taller Medioambiente | C3: Educativo | D3: Sede Social | E3: 200 | F3: 0
A4: 46172 | B4: Asamblea General | C4: Administrativo | D4: Online | E4: 0 | F4: 0

Sheet Finanzas
A1: Fecha | B1: Concepto | C1: Categoría | D1: Tipo | E1: Importe | F1: Evento
A2: 46032 | B2: Cuota socio 001 | C2: Cuotas | E2: 20 | F2: =IF(E2>0,"Ingreso","Gasto")
A3: 46037 | B3: Material oficina | C3: Material | E3: 45.5 | F3: =IF(E3>0,"Ingreso","Gasto")
A4: 46054 | B4: Alquiler local | C4: Gastos fijos | E4: 150 | F4: =IF(E4>0,"Ingreso","Gasto")
A5: 46063 | B5: Donación empresa X | C5: Donaciones | E5: 200 | F5: =IF(E5>0,"Ingreso","Gasto")
F6: =IF(A6="","",IF(E6>0,"Ingreso","Gasto"))
F7: =IF(A7="","",IF(E7>0,"Ingreso","Gasto"))
F8: =IF(A8="","",IF(E8>0,"Ingreso","Gasto"))
F9: =IF(A9="","",IF(E9>0,"Ingreso","Gasto"))
F10: =IF(A10="","",IF(E10>0,"Ingreso","Gasto"))
F11: =IF(A11="","",IF(E11>0,"Ingreso","Gasto"))
F12: =IF(A12="","",IF(E12>0,"Ingreso","Gasto"))
F13: =IF(A13="","",IF(E13>0,"Ingreso","Gasto"))
F14: =IF(A14="","",IF(E14>0,"Ingreso","Gasto"))
F15: =IF(A15="","",IF(E15>0,"Ingreso","Gasto"))
F16: =IF(A16="","",IF(E16>0,"Ingreso","Gasto"))
F17: =IF(A17="","",IF(E17>0,"Ingreso","Gasto"))
... F65: =IF(A65="","",IF(E65>0,"Ingreso","Gasto"))

Sheet Miembros
A1: Fecha Alta | B1: Nombre | C1: Tipo | D1: Activo | E1: Cuota
A2: 46027 | B2: Juan Pérez | C2: Voluntario | D2: Sí | E2: 0
A3: 46032 | B3: María García | C3: Socio | D3: Sí | E3: 20
A4: 46068 | B4: Asociación Amiga | C4: Colaborador | D4: Sí | E4: 0
