Workbook

Sheet Inicio
C2: Gestión de Eventos y Finanzas para Asociaciones
C3: Planifica eventos y controla las finanzas de tu asociación con esta herramienta profesional. Ideal para voluntarios y gestores de clubes.
C5: Cómo funciona
B6: 1. | C6: Ingresa los datos básicos de tu asociación en la hoja 'Configuración'
B7: 2. | C7: Registra eventos futuros en la hoja 'Calendario'
B8: 3. | C8: Anota todos los gastos e ingresos en la hoja 'Finanzas'
B9: 4. | C9: Asigna voluntarios a tareas específicas
B10: 5. | C10: Revisa el dashboard para ver el estado financiero
B11: 6. | C11: Exporta reportes para las reuniones de junta
C13: Rellene solo las celdas blancas: las columnas verdes se calculan solas.
C15: Ir a la hoja
C16: → Resumen
C17: → Eventos
C18: → Finanzas
C19: → Voluntarios
C21: Creado por Haiktec · haiktec.tech

Sheet Resumen
B2: Resumen – Gestión de Eventos y Finanzas para Asociaciones
B4: Indicadores
B5: Balance Total | C5: =SUM(Finanzas!D2:D300)
B6: Eventos próximos (30 días) | C6: =COUNTIFS(Eventos!A2:A100, ">"&TODAY(), Eventos!A2:A100, "<"&TODAY()+30)
B7: Voluntarios activos | C7: =COUNTIF(Voluntarios!F2:F100, ">0")
B8: Gastos por categoría | C8: =SUMIFS(Finanzas!D2:D300, Finanzas!C2:C300, "Gasto", Finanzas!F2:F300, "Materiales")
B9: Horas voluntariado | C9: =SUM(Voluntarios!F2:F100)
B10: Ingresos por cuotas | C10: =SUMIFS(Finanzas!D2:D300, Finanzas!F2:F300, "Cuotas")

Sheet Eventos
A1: Fecha | B1: Tipo de Evento | C1: Lugar | D1: Presupuesto | E1: Voluntarios Necesarios | F1: Estado
A2: 46096 | B2: Recaudación de fondos | C2: Plaza Mayor | D2: 500 | E2: 10 | F2: =IF(D2>0, IF(DATEDIF(TODAY(),A2,"d")<30, "Urgente", "Planificado"), "Gratis")
A3: 46134 | B3: Taller educativo | C3: Biblioteca | D3: 200 | E3: 5 | F3: =IF(D3>0, IF(DATEDIF(TODAY(),A3,"d")<30, "Urgente", "Planificado"), "Gratis")
A4: 46172 | B4: Asamblea general | C4: Sede social | D4: 0 | E4: 2 | F4: =IF(D4>0, IF(DATEDIF(TODAY(),A4,"d")<30, "Urgente", "Planificado"), "Gratis")
F5: =IF(A5="","",IF(D5>0, IF(DATEDIF(TODAY(),A5,"d")<30, "Urgente", "Planificado"), "Gratis"))
F6: =IF(A6="","",IF(D6>0, IF(DATEDIF(TODAY(),A6,"d")<30, "Urgente", "Planificado"), "Gratis"))
F7: =IF(A7="","",IF(D7>0, IF(DATEDIF(TODAY(),A7,"d")<30, "Urgente", "Planificado"), "Gratis"))
F8: =IF(A8="","",IF(D8>0, IF(DATEDIF(TODAY(),A8,"d")<30, "Urgente", "Planificado"), "Gratis"))
F9: =IF(A9="","",IF(D9>0, IF(DATEDIF(TODAY(),A9,"d")<30, "Urgente", "Planificado"), "Gratis"))
F10: =IF(A10="","",IF(D10>0, IF(DATEDIF(TODAY(),A10,"d")<30, "Urgente", "Planificado"), "Gratis"))
F11: =IF(A11="","",IF(D11>0, IF(DATEDIF(TODAY(),A11,"d")<30, "Urgente", "Planificado"), "Gratis"))
F12: =IF(A12="","",IF(D12>0, IF(DATEDIF(TODAY(),A12,"d")<30, "Urgente", "Planificado"), "Gratis"))
F13: =IF(A13="","",IF(D13>0, IF(DATEDIF(TODAY(),A13,"d")<30, "Urgente", "Planificado"), "Gratis"))
F14: =IF(A14="","",IF(D14>0, IF(DATEDIF(TODAY(),A14,"d")<30, "Urgente", "Planificado"), "Gratis"))
F15: =IF(A15="","",IF(D15>0, IF(DATEDIF(TODAY(),A15,"d")<30, "Urgente", "Planificado"), "Gratis"))
F16: =IF(A16="","",IF(D16>0, IF(DATEDIF(TODAY(),A16,"d")<30, "Urgente", "Planificado"), "Gratis"))
... F54: =IF(A54="","",IF(D54>0, IF(DATEDIF(TODAY(),A54,"d")<30, "Urgente", "Planificado"), "Gratis"))

Sheet Finanzas
A1: Fecha | B1: Concepto | C1: Tipo | D1: Cantidad | E1: Evento Relacionado | F1: Categoría
A2: 46032 | B2: Materiales taller | C2: Gasto | D2: =IF(C2="Gasto", -ABS(D2), ABS(D2)) | E2: Taller educativo | F2: Materiales
A3: 46068 | B3: Cuota socio 12345 | C3: Ingreso | D3: =IF(C3="Gasto", -ABS(D3), ABS(D3)) | F3: Cuotas
A4: 46073 | B4: Alquiler local | C4: Gasto | D4: =IF(C4="Gasto", -ABS(D4), ABS(D4)) | F4: Gastos fijos
D5: =IF(A5="","",IF(C5="Gasto", -ABS(D5), ABS(D5)))
D6: =IF(A6="","",IF(C6="Gasto", -ABS(D6), ABS(D6)))
D7: =IF(A7="","",IF(C7="Gasto", -ABS(D7), ABS(D7)))
D8: =IF(A8="","",IF(C8="Gasto", -ABS(D8), ABS(D8)))
D9: =IF(A9="","",IF(C9="Gasto", -ABS(D9), ABS(D9)))
D10: =IF(A10="","",IF(C10="Gasto", -ABS(D10), ABS(D10)))
D11: =IF(A11="","",IF(C11="Gasto", -ABS(D11), ABS(D11)))
D12: =IF(A12="","",IF(C12="Gasto", -ABS(D12), ABS(D12)))
D13: =IF(A13="","",IF(C13="Gasto", -ABS(D13), ABS(D13)))
D14: =IF(A14="","",IF(C14="Gasto", -ABS(D14), ABS(D14)))
D15: =IF(A15="","",IF(C15="Gasto", -ABS(D15), ABS(D15)))
D16: =IF(A16="","",IF(C16="Gasto", -ABS(D16), ABS(D16)))
... D204: =IF(A204="","",IF(C204="Gasto", -ABS(D204), ABS(D204)))

Sheet Voluntarios
A1: Nombre | B1: Teléfono | C1: Email | D1: Disponibilidad | E1: Habilidades | F1: Horas Contabilizadas
A2: Juan Pérez | B2: 600123456 | C2: juan@ejemplo.com | D2: Fines de semana | E2: Logística, Cocina
A3: María López | B3: 655987654 | C3: maria@ejemplo.com | D3: Tardes | E3: Contabilidad
