Workbook

Sheet Start
C2: NRW Family City Trip Budget Planner & Itinerary Tracker
C3: Plan your perfect family city break in NRW with this all-in-one budget and itinerary tracker - save money while creating unforgettable memories.
C5: How it works
B6: 1. | C6: Enter your trip dates and destinations
B7: 2. | C7: Add planned attractions with costs & booking details
B8: 3. | C8: Track daily expenses with smart categories
B9: 4. | C9: Compare budget vs actual spending
B10: 5. | C10: Get automatic recommendations for savings
B11: 6. | C11: Export your final trip report
C13: Only fill in white cells – green columns calculate automatically.
C15: Go to sheet
C16: → Dashboard
C17: → Trip Planner
C18: → Daily Budget
C19: → Itinerary
C21: Made by Haiktec · haiktec.tech

Sheet Dashboard
B2: Dashboard – NRW Family City Trip Budget Planner & Itinerary Tracker
B4: Key figures
B5: Total Trip Budget | C5: =SUM('Daily Budget'!C2:C300)
B6: Total Actual Costs | C6: =SUM('Daily Budget'!D2:D300)
B7: Savings Potential | C7: =SUMIF('Daily Budget'!E2:E300,">0")
B8: Activities Planned | C8: =COUNTA('Trip Planner'!A2:A300)
B9: Days Until Trip | C9: =MIN('Trip Planner'!A2:A300)-TODAY()

Sheet Trip Planner
A1: Date | B1: Destination | C1: Attraction | D1: Adult Price | E1: Child Price | F1: Family Ticket | G1: Booked
A2: 46127 | B2: Cologne | C2: Cologne Zoo | D2: 25 | E2: 12.5 | F2: =D2+E2*2 | G2: Yes
A3: 46128 | B3: Düsseldorf | C3: Aquazoo Löbbecke Museum | D3: 18 | E3: 9 | F3: =D3+E3*2 | G3: No
A4: 46129 | B4: Essen | C4: Zollverein Coal Mine | D4: 15 | E4: 7.5 | F4: =D4+E4*2 | G4: Yes
F5: =IF(A5="","",D5+E5*2)
F6: =IF(A6="","",D6+E6*2)
F7: =IF(A7="","",D7+E7*2)
F8: =IF(A8="","",D8+E8*2)
F9: =IF(A9="","",D9+E9*2)
F10: =IF(A10="","",D10+E10*2)
F11: =IF(A11="","",D11+E11*2)
F12: =IF(A12="","",D12+E12*2)
F13: =IF(A13="","",D13+E13*2)
F14: =IF(A14="","",D14+E14*2)
F15: =IF(A15="","",D15+E15*2)
F16: =IF(A16="","",D16+E16*2)
... F54: =IF(A54="","",D54+E54*2)

Sheet Daily Budget
A1: Date | B1: Category | C1: Planned | D1: Actual | E1: Difference
A2: 46127 | B2: Transport | C2: 50 | D2: 42.3 | E2: =C2-D2
A3: 46127 | B3: Food | C3: 80 | D3: 92.5 | E3: =C3-D3
A4: 46127 | B4: Activities | C4: 100 | D4: 115 | E4: =C4-D4
E5: =IF(A5="","",C5-D5)
E6: =IF(A6="","",C6-D6)
E7: =IF(A7="","",C7-D7)
E8: =IF(A8="","",C8-D8)
E9: =IF(A9="","",C9-D9)
E10: =IF(A10="","",C10-D10)
E11: =IF(A11="","",C11-D11)
E12: =IF(A12="","",C12-D12)
E13: =IF(A13="","",C13-D13)
E14: =IF(A14="","",C14-D14)
E15: =IF(A15="","",C15-D15)
E16: =IF(A16="","",C16-D16)
... E104: =IF(A104="","",C104-D104)

Sheet Itinerary
A1: Date | B1: Time | C1: Activity | D1: Location | E1: Notes
A2: 46127 | B2: 09:00 | C2: Zoo Visit | D2: Cologne Zoo | E2: Meet at main entrance
A3: 46127 | B3: 12:30 | C3: Lunch | D3: Brauhaus Sion | E3: Reservation under Müller
A4: 46127 | B4: 15:00 | C4: Cathedral Tour | D4: Cologne Cathedral | E4: Guided family tour
