Workbook

Sheet Inicio
C2: Planificador de Mudanza y Renovación Profesional: Control de Presupuesto y Tiempo
C3: Herramienta todo en uno para controlar costes y plazos de mudanzas y renovaciones. Simplifica la gestión de presupuestos y evita sorpresas.
C5: Cómo funciona
B6: 1. | C6: Registra todos los gastos en las hojas correspondientes
B7: 2. | C7: Clasifica cada entrada por categoría usando los desplegables
B8: 3. | C8: Revisa el dashboard para ver el estado actual
B9: 4. | C9: Ajusta tu presupuesto según el análisis de gastos
B10: 5. | C10: Programa fechas clave en el calendario
C12: Rellene solo las celdas blancas: las columnas verdes se calculan solas.
C14: Ir a la hoja
C15: → Resumen
C16: → Gastos
C17: → Calendario
C19: Creado por Haiktec · haiktec.tech

Sheet Resumen
B2: Resumen – Planificador de Mudanza y Renovación Profesional: Control de
B4: Indicadores
B5: Gasto total | C5: =SUM('Gastos'!F2:F300)
B6: Gasto materiales | C6: =SUMIF('Gastos'!B2:B300,"Material",'Gastos'!F2:F300)
B7: Gasto mano obra | C7: =SUMIF('Gastos'!B2:B300,"Mano de obra",'Gastos'!F2:F300)
B8: Hitos pendientes | C8: =COUNTIF('Calendario'!D2:D300,"Pendiente")
B9: Promedio diario | C9: =AVERAGE('Gastos'!F2:F300)
B10: Días hasta mudanza | C10: =MIN('Calendario'!A2:A300)-TODAY()

Sheet Gastos
A1: Fecha | B1: Categoría | C1: Concepto | D1: Cantidad | E1: Precio | F1: Total
A2: 46091 | B2: Material | C2: Cajas de embalaje | D2: 15 | E2: 2.5 | F2: =D2*E2
A3: 46093 | B3: Transporte | C3: Furgoneta alquiler | D3: 1 | E3: 60 | F3: =D3*E3
A4: 46096 | B4: Mano de obra | C4: Montaje muebles | D4: 4 | E4: 25 | F4: =D4*E4
A5: 46099 | B5: Material | C5: Pintura paredes | D5: 5 | E5: 18.75 | F5: =D5*E5
F6: =IF(A6="","",D6*E6)
F7: =IF(A7="","",D7*E7)
F8: =IF(A8="","",D8*E8)
F9: =IF(A9="","",D9*E9)
F10: =IF(A10="","",D10*E10)
F11: =IF(A11="","",D11*E11)
F12: =IF(A12="","",D12*E12)
F13: =IF(A13="","",D13*E13)
F14: =IF(A14="","",D14*E14)
F15: =IF(A15="","",D15*E15)
F16: =IF(A16="","",D16*E16)
F17: =IF(A17="","",D17*E17)
... F105: =IF(A105="","",D105*E105)

Sheet Calendario
A1: Fecha | B1: Hito | C1: Días restantes | D1: Estado
A2: 46117 | B2: Finalizar embalaje | C2: =A2-TODAY() | D2: =IF(C2<0,"Atrasado",IF(C2=0,"Hoy","En plazo"))
A3: 46124 | B3: Entrega llaves nuevo local | C3: =A3-TODAY() | D3: =IF(C3<0,"Atrasado",IF(C3=0,"Hoy","En plazo"))
A4: 46127 | B4: Finalizar reformas baño | C4: =A4-TODAY() | D4: =IF(C4<0,"Atrasado",IF(C4=0,"Hoy","En plazo"))
C5: =IF(A5="","",A5-TODAY()) | D5: =IF(A5="","",IF(C5<0,"Atrasado",IF(C5=0,"Hoy","En plazo")))
C6: =IF(A6="","",A6-TODAY()) | D6: =IF(A6="","",IF(C6<0,"Atrasado",IF(C6=0,"Hoy","En plazo")))
C7: =IF(A7="","",A7-TODAY()) | D7: =IF(A7="","",IF(C7<0,"Atrasado",IF(C7=0,"Hoy","En plazo")))
C8: =IF(A8="","",A8-TODAY()) | D8: =IF(A8="","",IF(C8<0,"Atrasado",IF(C8=0,"Hoy","En plazo")))
C9: =IF(A9="","",A9-TODAY()) | D9: =IF(A9="","",IF(C9<0,"Atrasado",IF(C9=0,"Hoy","En plazo")))
C10: =IF(A10="","",A10-TODAY()) | D10: =IF(A10="","",IF(C10<0,"Atrasado",IF(C10=0,"Hoy","En plazo")))
C11: =IF(A11="","",A11-TODAY()) | D11: =IF(A11="","",IF(C11<0,"Atrasado",IF(C11=0,"Hoy","En plazo")))
C12: =IF(A12="","",A12-TODAY()) | D12: =IF(A12="","",IF(C12<0,"Atrasado",IF(C12=0,"Hoy","En plazo")))
C13: =IF(A13="","",A13-TODAY()) | D13: =IF(A13="","",IF(C13<0,"Atrasado",IF(C13=0,"Hoy","En plazo")))
C14: =IF(A14="","",A14-TODAY()) | D14: =IF(A14="","",IF(C14<0,"Atrasado",IF(C14=0,"Hoy","En plazo")))
C15: =IF(A15="","",A15-TODAY()) | D15: =IF(A15="","",IF(C15<0,"Atrasado",IF(C15=0,"Hoy","En plazo")))
C16: =IF(A16="","",A16-TODAY()) | D16: =IF(A16="","",IF(C16<0,"Atrasado",IF(C16=0,"Hoy","En plazo")))
... C34: =IF(A34="","",A34-TODAY()) | D34: =IF(A34="","",IF(C34<0,"Atrasado",IF(C34=0,"Hoy","En plazo")))
