Workbook

Sheet Accueil
C2: Planificateur de Soins et Budget pour Aidants Familiaux
C3: Optimisez l'organisation des soins et le suivi des dépenses pour vos proches dépendants. Un outil clé-en-main pour les aidants familiaux et petites structures d'aide à domicile.
C5: Mode d'emploi
B6: 1. | C6: Saisissez les rendez-vous médicaux et soins à prodiguer
B7: 2. | C7: Enregistrez les dépenses (médicaments, matériel, etc.)
B8: 3. | C8: Suivez les prescriptions médicales avec rappels
B9: 4. | C9: Visualisez le budget consacré aux soins
B10: 5. | C10: Géneźreź des rapports pour le médecin ou l'administration
B11: 6. | C11: Exportez les données pour partager avec les autres aidants
C13: Remplissez uniquement les cellules blanches – les colonnes vertes se calculent seules.
C15: Aller à la feuille
C16: → Tableau de bord
C17: → Rendez-vous et soins
C18: → Dépenses
C19: → Traitements
C21: Créé par Haiktec · haiktec.tech

Sheet Tableau de bord
B2: Tableau de bord – Planificateur de Soins et Budget pour Aidants Familiaux
B4: Indicateurs
B5: Dépenses totales | C5: =SUM(Dépenses!D2:D300)
B6: Remboursements | C6: =SUM(Dépenses!F2:F300)
B7: Coût net | C7: =KPI1-KPI2
B8: Soins à venir | C8: =COUNTIF('Rendez-vous et soins'!A2:A300,">="&TODAY())
B9: Médicaments actifs | C9: =COUNTA(Traitements!A2:A30)
B10: Soins effectués | C10: =COUNTIF('Rendez-vous et soins'!E2:E300,"Effectué")

Sheet Rendez-vous et soins
A1: Date | B1: Type | C1: Soin à effectuer | D1: Préparé par | E1: Statut
A2: 46068 | B2: Médical | C2: Consultation cardiologue | D2: Fille | E2: Confirmé
A3: 46073 | B3: Soin | C3: Prise de tension | D3: Aide à domicile
A4: 46082 | B4: Médical | C4: Renouvellement ordonnance | D4: Fils
A5: 46081 | B5: Soin | C5: Toilette | D5: Aide à domicile | E5: Effectué
A6: 46069 | B6: Administratif | C6: Dossier APA | D6: Conjoint | E6: En cours

Sheet Dépenses
A1: Date | B1: Catégorie | C1: Description | D1: Montant | E1: Remboursable | F1: Montant remboursé
A2: 46032 | B2: Médicaments | C2: Doliprane | D2: 5.2 | E2: Oui | F2: =IF(E2="Oui",ROUND(D2*0.75,2),IF(E2="Partiel",D2*0.5,0))
A3: 46037 | B3: Matériel | C3: Protège-matelas | D3: 89 | E3: Non | F3: =IF(E3="Oui",ROUND(D3*0.75,2),IF(E3="Partiel",D3*0.5,0))
A4: 46042 | B4: Transport | C4: Taxi consultation | D4: 35 | E4: Partiel | F4: =IF(E4="Oui",ROUND(D4*0.75,2),IF(E4="Partiel",D4*0.5,0))
A5: 46058 | B5: Médicaments | C5: Traitement BPCO | D5: 12.3 | E5: Oui | F5: =IF(E5="Oui",ROUND(D5*0.75,2),IF(E5="Partiel",D5*0.5,0))
F6: =IF(A6="","",IF(E6="Oui",ROUND(D6*0.75,2),IF(E6="Partiel",D6*0.5,0)))
F7: =IF(A7="","",IF(E7="Oui",ROUND(D7*0.75,2),IF(E7="Partiel",D7*0.5,0)))
F8: =IF(A8="","",IF(E8="Oui",ROUND(D8*0.75,2),IF(E8="Partiel",D8*0.5,0)))
F9: =IF(A9="","",IF(E9="Oui",ROUND(D9*0.75,2),IF(E9="Partiel",D9*0.5,0)))
F10: =IF(A10="","",IF(E10="Oui",ROUND(D10*0.75,2),IF(E10="Partiel",D10*0.5,0)))
F11: =IF(A11="","",IF(E11="Oui",ROUND(D11*0.75,2),IF(E11="Partiel",D11*0.5,0)))
F12: =IF(A12="","",IF(E12="Oui",ROUND(D12*0.75,2),IF(E12="Partiel",D12*0.5,0)))
F13: =IF(A13="","",IF(E13="Oui",ROUND(D13*0.75,2),IF(E13="Partiel",D13*0.5,0)))
F14: =IF(A14="","",IF(E14="Oui",ROUND(D14*0.75,2),IF(E14="Partiel",D14*0.5,0)))
F15: =IF(A15="","",IF(E15="Oui",ROUND(D15*0.75,2),IF(E15="Partiel",D15*0.5,0)))
F16: =IF(A16="","",IF(E16="Oui",ROUND(D16*0.75,2),IF(E16="Partiel",D16*0.5,0)))
F17: =IF(A17="","",IF(E17="Oui",ROUND(D17*0.75,2),IF(E17="Partiel",D17*0.5,0)))
... F105: =IF(A105="","",IF(E105="Oui",ROUND(D105*0.75,2),IF(E105="Partiel",D105*0.5,0)))

Sheet Traitements
A1: Médicament | B1: Posologie | C1: Heure | D1: Détails | E1: Dernière prise
A2: Doliprane | B2: 1 comprimé | C2: 8h et 20h | D2: Si douleur | E2: 46067
A3: Tensiomètre | B3: 2 mesures/jour | C3: Matin et soir | D3: Noter valeurs | E3: 46068
