Workbook

Sheet Accueil
C2: Planificateur de Budget de Mariage & Suivi des Dépenses - Modèle Professionnel 2026
C3: Suivi précis de toutes les dépenses du mariage, analyse automatique par catégorie et prévision du budget restant. Conçu par des experts pour éviter les mauvaises surprises financières.
C5: Mode d'emploi
B6: 1. | C6: Entrez votre budget total initial
B7: 2. | C7: Ajoutez vos réservations et dépenses au fur et à mesure
B8: 3. | C8: Consultez l'analyse automatique par catégorie
B9: 4. | C9: Suivez les paiements restants avec les échéances
B10: 5. | C10: Exportez les rapports pour partager avec vos prestataires
C12: Remplissez uniquement les cellules blanches – les colonnes vertes se calculent seules.
C14: Aller à la feuille
C15: → Tableau de bord
C16: → Dépenses
C17: → Budget
C18: → Dashboard
C20: Créé par Haiktec · haiktec.tech

Sheet Tableau de bord
B2: Tableau de bord – Planificateur de Budget de Mariage & Suivi des Dépenses - Mo
B4: Indicateurs
B5: Budget Total Initial | C5: =SUM(Budget!B2:B20)
B6: Dépenses Totales | C6: =SUM(Dépenses!D2:D300)
B7: Reste à Payer | C7: =SUMIF(Dépenses!E2:E300, "À payer", Dépenses!D2:D300)+SUMIF(Dépenses!E2:E300, "Acompte", Dépenses!D2:D300)*0.5
B8: Nombre de Prestataires | C8: =COUNTA(Dépenses!B2:B300)
B9: Dépenses Moyennes par Catégorie | C9: =AVERAGE(Budget!C2:C20)
B10: Catégorie la Plus Coûteuse | C10: =INDEX(Budget!A2:A20, MATCH(MAX(Budget!C2:C20), Budget!C2:C20, 0))

Sheet Dépenses
A1: Date | B1: Fournisseur | C1: Catégorie | D1: Montant | E1: Statut Paiement | F1: Échéance
A2: 46096 | B2: Fleuriste Douceur | C2: Fleurs | D2: 850 | E2: Payé | F2: 46091
A3: 46114 | B3: Traiteur Élégance | C3: Nourriture | D3: 3200 | E3: Acompte | F3: 46157
A4: 46081 | B4: Salle Belle Vue | C4: Location | D4: 2500 | E4: Payé | F4: 46081
A5: 46122 | B5: Photographie Lumière | C5: Photos | D5: 1800 | E5: À payer | F5: 46162
A6: 46103 | B6: DJ Harmonie | C6: Musique | D6: 900 | E6: Acompte | F6: 46174
A7: 46068 | B7: Robes Étoile | C7: Tenues | D7: 1200 | E7: Payé | F7: 46068
A8: 46086 | B8: Transport Luxe | C8: Logistique | D8: 600 | E8: À payer | F8: 46167
A9: 46130 | B9: Décors Féerique | C9: Décoration | D9: 750 | E9: Acompte | F9: 46152

Sheet Budget
A1: Catégorie | B1: Budget Initial | C1: Dépenses | D1: Reste
A2: Fleurs | B2: 1000 | C2: =SUMIF(Dépenses!C2:C100, A2, Dépenses!D2:D100) | D2: =B2-C2
A3: Nourriture | B3: 3500 | C3: =SUMIF(Dépenses!C2:C100, A3, Dépenses!D2:D100) | D3: =B3-C3
A4: Location | B4: 2500 | C4: =SUMIF(Dépenses!C2:C100, A4, Dépenses!D2:D100) | D4: =B4-C4
A5: Photos | B5: 2000 | C5: =SUMIF(Dépenses!C2:C100, A5, Dépenses!D2:D100) | D5: =B5-C5
A6: Musique | B6: 1000 | C6: =SUMIF(Dépenses!C2:C100, A6, Dépenses!D2:D100) | D6: =B6-C6
A7: Tenues | B7: 1500 | C7: =SUMIF(Dépenses!C2:C100, A7, Dépenses!D2:D100) | D7: =B7-C7
A8: Logistique | B8: 800 | C8: =SUMIF(Dépenses!C2:C100, A8, Dépenses!D2:D100) | D8: =B8-C8
A9: Décoration | B9: 1000 | C9: =SUMIF(Dépenses!C2:C100, A9, Dépenses!D2:D100) | D9: =B9-C9
C10: =IF(A10="","",SUMIF(Dépenses!C2:C100, A10, Dépenses!D2:D100)) | D10: =IF(A10="","",B10-C10)
C11: =IF(A11="","",SUMIF(Dépenses!C2:C100, A11, Dépenses!D2:D100)) | D11: =IF(A11="","",B11-C11)
C12: =IF(A12="","",SUMIF(Dépenses!C2:C100, A12, Dépenses!D2:D100)) | D12: =IF(A12="","",B12-C12)
C13: =IF(A13="","",SUMIF(Dépenses!C2:C100, A13, Dépenses!D2:D100)) | D13: =IF(A13="","",B13-C13)
C14: =IF(A14="","",SUMIF(Dépenses!C2:C100, A14, Dépenses!D2:D100)) | D14: =IF(A14="","",B14-C14)
C15: =IF(A15="","",SUMIF(Dépenses!C2:C100, A15, Dépenses!D2:D100)) | D15: =IF(A15="","",B15-C15)
C16: =IF(A16="","",SUMIF(Dépenses!C2:C100, A16, Dépenses!D2:D100)) | D16: =IF(A16="","",B16-C16)
C17: =IF(A17="","",SUMIF(Dépenses!C2:C100, A17, Dépenses!D2:D100)) | D17: =IF(A17="","",B17-C17)
C18: =IF(A18="","",SUMIF(Dépenses!C2:C100, A18, Dépenses!D2:D100)) | D18: =IF(A18="","",B18-C18)
C19: =IF(A19="","",SUMIF(Dépenses!C2:C100, A19, Dépenses!D2:D100)) | D19: =IF(A19="","",B19-C19)

Sheet Dashboard
A1: Métrique | B1: Valeur
