Workbook

Sheet Inicio
C2: Planificador de Presupuesto y Control de Gastos para Bodas
C3: Simplifica la planificación de tu boda con este práctico planificador. Mantén el control de todos los gastos y asegúrate de cumplir con tu presupuesto.
C5: Cómo funciona
B6: 1. | C6: Introduce tus datos básicos y tu presupuesto inicial.
B7: 2. | C7: Registra cada gasto por categoría (banquete, fotografía, decoración, etc.).
B8: 3. | C8: Utiliza los filtros para ver los gastos por categoría o por proveedor.
B9: 4. | C9: Revisa los gráficos para obtener una visión general de tu situación financiera.
B10: 5. | C10: Ajusta tu presupuesto en función de los gastos reales.
B11: 6. | C11: Descarga un informe detallado para compartir con los proveedores y familiares.
C13: Rellene solo las celdas blancas: las columnas verdes se calculan solas.
C15: Ir a la hoja
C16: → Resumen
C17: → Gastos
C18: → Presupuesto
C20: Creado por Haiktec · haiktec.tech

Sheet Resumen
B2: Resumen – Planificador de Presupuesto y Control de Gastos para Bodas
B4: Indicadores
B5: Presupuesto Total | C5: =SUM(Presupuesto!B2:B20)
B6: Gastos Totales | C6: =SUM(Presupuesto!C2:C20)
B7: Saldo Restante | C7: =SUM(Presupuesto!D2:D20)
B8: Número de Gastos | C8: =COUNTA(Gastos!A2:A300)

Sheet Gastos
A1: Fecha | B1: Categoria | C1: Proveedor | D1: Descripcion | E1: Cantidad | F1: Precio Unitario | G1: Total
A2: 46188 | B2: Banquete | C2: Restaurante Azul | D2: Menú para 100 personas | E2: 100 | F2: 50 | G2: =E2*F2
A3: 46193 | B3: Fotografía | C3: FotosPerfectas | D3: Fotos y vídeo | E3: 1 | F3: 1500 | G3: =E3*F3
A4: 46198 | B4: Decoracion | C4: Floristería Bella | D4: Arreglos florales | E4: 10 | F4: 80 | G4: =E4*F4
A5: 46204 | B5: Musica | C5: DjMúsica | D5: Servicio DJ | E5: 1 | F5: 800 | G5: =E5*F5
G6: =IF(A6="","",E6*F6)
G7: =IF(A7="","",E7*F7)
G8: =IF(A8="","",E8*F8)
G9: =IF(A9="","",E9*F9)
G10: =IF(A10="","",E10*F10)
G11: =IF(A11="","",E11*F11)
G12: =IF(A12="","",E12*F12)
G13: =IF(A13="","",E13*F13)
G14: =IF(A14="","",E14*F14)
G15: =IF(A15="","",E15*F15)
G16: =IF(A16="","",E16*F16)
G17: =IF(A17="","",E17*F17)
... G65: =IF(A65="","",E65*F65)

Sheet Presupuesto
A1: Categoria | B1: Presupuesto Inicial | C1: Gastos Totales | D1: Diferencia
A2: Banquete | B2: 5000 | C2: =SUMIF(Gastos!B2:B300,A2,Gastos!G2:G300) | D2: =B2-C2
A3: Fotografía | B3: 1500 | C3: =SUMIF(Gastos!B2:B300,A3,Gastos!G2:G300) | D3: =B3-C3
A4: Decoracion | B4: 800 | C4: =SUMIF(Gastos!B2:B300,A4,Gastos!G2:G300) | D4: =B4-C4
A5: Musica | B5: 800 | C5: =SUMIF(Gastos!B2:B300,A5,Gastos!G2:G300) | D5: =B5-C5
C6: =IF(A6="","",SUMIF(Gastos!B2:B300,A6,Gastos!G2:G300)) | D6: =IF(A6="","",B6-C6)
C7: =IF(A7="","",SUMIF(Gastos!B2:B300,A7,Gastos!G2:G300)) | D7: =IF(A7="","",B7-C7)
C8: =IF(A8="","",SUMIF(Gastos!B2:B300,A8,Gastos!G2:G300)) | D8: =IF(A8="","",B8-C8)
C9: =IF(A9="","",SUMIF(Gastos!B2:B300,A9,Gastos!G2:G300)) | D9: =IF(A9="","",B9-C9)
C10: =IF(A10="","",SUMIF(Gastos!B2:B300,A10,Gastos!G2:G300)) | D10: =IF(A10="","",B10-C10)
C11: =IF(A11="","",SUMIF(Gastos!B2:B300,A11,Gastos!G2:G300)) | D11: =IF(A11="","",B11-C11)
C12: =IF(A12="","",SUMIF(Gastos!B2:B300,A12,Gastos!G2:G300)) | D12: =IF(A12="","",B12-C12)
C13: =IF(A13="","",SUMIF(Gastos!B2:B300,A13,Gastos!G2:G300)) | D13: =IF(A13="","",B13-C13)
C14: =IF(A14="","",SUMIF(Gastos!B2:B300,A14,Gastos!G2:G300)) | D14: =IF(A14="","",B14-C14)
C15: =IF(A15="","",SUMIF(Gastos!B2:B300,A15,Gastos!G2:G300)) | D15: =IF(A15="","",B15-C15)
C16: =IF(A16="","",SUMIF(Gastos!B2:B300,A16,Gastos!G2:G300)) | D16: =IF(A16="","",B16-C16)
C17: =IF(A17="","",SUMIF(Gastos!B2:B300,A17,Gastos!G2:G300)) | D17: =IF(A17="","",B17-C17)
C18: =IF(A18="","",SUMIF(Gastos!B2:B300,A18,Gastos!G2:G300)) | D18: =IF(A18="","",B18-C18)
C19: =IF(A19="","",SUMIF(Gastos!B2:B300,A19,Gastos!G2:G300)) | D19: =IF(A19="","",B19-C19)
C20: =IF(A20="","",SUMIF(Gastos!B2:B300,A20,Gastos!G2:G300)) | D20: =IF(A20="","",B20-C20)
C21: =IF(A21="","",SUMIF(Gastos!B2:B300,A21,Gastos!G2:G300)) | D21: =IF(A21="","",B21-C21)
C22: =IF(A22="","",SUMIF(Gastos!B2:B300,A22,Gastos!G2:G300)) | D22: =IF(A22="","",B22-C22)
C23: =IF(A23="","",SUMIF(Gastos!B2:B300,A23,Gastos!G2:G300)) | D23: =IF(A23="","",B23-C23)
C24: =IF(A24="","",SUMIF(Gastos!B2:B300,A24,Gastos!G2:G300)) | D24: =IF(A24="","",B24-C24)
C25: =IF(A25="","",SUMIF(Gastos!B2:B300,A25,Gastos!G2:G300)) | D25: =IF(A25="","",B25-C25)
