Workbook

Sheet 开始
C2: 智能搬迁与装修预算追踪器 - 2026专业版
C3: 一站式管理您的搬迁和装修开支，自动计算总成本并提供可视化的花费分析，帮您节省高达20%的预算
C5: 使用说明
B6: 1. | C6: 填写基本信息表设置总预算
B7: 2. | C7: 在“开支记录”页录入每笔费用
B8: 3. | C8: 使用“供应商比较”页评估报价
B9: 4. | C9: 查看仪表盘掌握实时预算状态
B10: 5. | C10: 根据预警调整开支计划
C12: 只需填写白色单元格，绿色列会自动计算。
C14: 打开工作表
C15: → 总览
C16: → 开支记录
C17: → 供应商比较
C18: → 仪表盘
C20: 由 Haiktec 制作 · haiktec.tech

Sheet 总览
B2: 总览 – 智能搬迁与装修预算追踪器 - 2026专业版
B4: 关键指标
B5: 总支出 | C5: =SUM('开支记录'!G2:G300)
B6: 剩余预算 | C6: =B2-'开支记录'!G300
B7: 装修材料占比 | C7: =SUMIF('开支记录'!B2:B300,"装修材料",'开支记录'!G2:G300)/SUM('开支记录'!G2:G300)
B8: 优选供应商数 | C8: =COUNTIF('供应商比较'!E2:E20,"✓")
B9: 日均支出 | C9: =AVERAGE('开支记录'!G2:G300)
B10: 最高单笔支出 | C10: =MAX('开支记录'!G2:G300)

Sheet 开支记录
A1: 日期 | B1: 类别 | C1: 项目 | D1: 供应商 | E1: 数量 | F1: 单价 | G1: 总价
A2: 46091 | B2: 装修材料 | C2: 墙面漆 | D2: 立邦专卖店 | E2: 2 | F2: 350 | G2: =E2*F2
A3: 46093 | B3: 人工费 | C3: 水电改造 | D3: 李师傅团队 | E3: 1 | F3: 1200 | G3: =E3*F3
A4: 46096 | B4: 搬迁服务 | C4: 家具搬运 | D4: 蚂蚁搬家 | E4: 1 | F4: 800 | G4: =E4*F4
A5: 46099 | B5: 装修材料 | C5: 地砖 | D5: 马可波罗 | E5: 25 | F5: 68 | G5: =E5*F5
A6: 46101 | B6: 设计费 | C6: 空间设计 | D6: 张设计师 | E6: 1 | F6: 3000 | G6: =E6*F6
G7: =IF(A7="","",E7*F7)
G8: =IF(A8="","",E8*F8)
G9: =IF(A9="","",E9*F9)
G10: =IF(A10="","",E10*F10)
G11: =IF(A11="","",E11*F11)
G12: =IF(A12="","",E12*F12)
G13: =IF(A13="","",E13*F13)
G14: =IF(A14="","",E14*F14)
G15: =IF(A15="","",E15*F15)
G16: =IF(A16="","",E16*F16)
G17: =IF(A17="","",E17*F17)
G18: =IF(A18="","",E18*F18)
... G106: =IF(A106="","",E106*F106)

Sheet 供应商比较
A1: 供应商名称 | B1: 服务类型 | C1: 报价 | D1: 评分 | E1: 选择
A2: 蚂蚁搬家 | B2: 搬迁服务 | C2: 800 | D2: 4.5 | E2: =IF(D2>=4.5,"✓","")
A3: 自如装修 | B3: 全包装修 | C3: 85000 | D3: 4.2 | E3: =IF(D3>=4.5,"✓","")
A4: 李师傅团队 | B4: 水电工程 | C4: 1200 | D4: 4.8 | E4: =IF(D4>=4.5,"✓","")
E5: =IF(A5="","",IF(D5>=4.5,"✓",""))
E6: =IF(A6="","",IF(D6>=4.5,"✓",""))
E7: =IF(A7="","",IF(D7>=4.5,"✓",""))
E8: =IF(A8="","",IF(D8>=4.5,"✓",""))
E9: =IF(A9="","",IF(D9>=4.5,"✓",""))
E10: =IF(A10="","",IF(D10>=4.5,"✓",""))
E11: =IF(A11="","",IF(D11>=4.5,"✓",""))
E12: =IF(A12="","",IF(D12>=4.5,"✓",""))
E13: =IF(A13="","",IF(D13>=4.5,"✓",""))
E14: =IF(A14="","",IF(D14>=4.5,"✓",""))
E15: =IF(A15="","",IF(D15>=4.5,"✓",""))
E16: =IF(A16="","",IF(D16>=4.5,"✓",""))
... E24: =IF(A24="","",IF(D24>=4.5,"✓",""))

Sheet 仪表盘
A1: 指标 | B1: 数值
