Workbook

Sheet Start
C2: Smart Female Fitness Coach Business Planner
C3: Manage your fitness coaching business with ease - track clients, income, expenses, and progress all in one professional tool designed specifically for female trainers.
C5: How it works
B6: 1. | C6: Enter your clients' basic information
B7: 2. | C7: Schedule training sessions
B8: 3. | C8: Track income from each client
B9: 4. | C9: Monitor business expenses
B10: 5. | C10: Check your dashboard for key metrics
B11: 6. | C11: Customize categories as needed
B12: 7. | C12: Regularly update for accurate tracking
C14: Only fill in white cells – green columns calculate automatically.
C16: Go to sheet
C17: → Dashboard
C18: → Clients
C19: → Income
C20: → Expenses
C22: Made by Haiktec · haiktec.tech

Sheet Dashboard
B2: Dashboard – Smart Female Fitness Coach Business Planner
B4: Key figures
B5: Total Monthly Income | C5: =SUMIF(Income!A2:A100,">="&DATE(YEAR(TODAY()),MONTH(TODAY()),1),Income!C2:C100)
B6: Total Monthly Expenses | C6: =SUMIF(Expenses!A2:A100,">="&DATE(YEAR(TODAY()),MONTH(TODAY()),1),Expenses!D2:D100)
B7: Active Clients | C7: =COUNTIF(Clients!F2:F100,"Active")
B8: Average Session Value | C8: =AVERAGE(Income!C2:C100)
B9: Client Retention Rate | C9: =COUNTIF(Clients!B2:B100,"<="&EDATE(TODAY(),-6))/COUNTIF(Clients!B2:B100,"<>"&"")
B10: Profit Margin | C10: =(KPI1-KPI2)/KPI1

Sheet Clients
A1: Name | B1: Join Date | C1: Plan | D1: Sessions Week | E1: Last Payment | F1: Status
A2: Sarah Miller | B2: 46096 | C2: Premium | D2: 3 | E2: 46113 | F2: Active
A3: Emma Wilson | B3: 46063 | C3: Basic | D3: 2 | E3: 46109 | F3: Active
A4: Olivia Brown | B4: 46027 | C4: Premium | D4: 3 | E4: 46096 | F4: Paused
A5: Sophia Davis | B5: 46082 | C5: Basic | D5: 1 | E5: 46112 | F5: Active

Sheet Income
A1: Date | B1: Client | C1: Amount | D1: Type | E1: Status
A2: 46082 | B2: Sarah Miller | C2: 120 | D2: Session | E2: =IF(TODAY()-A2>7,"Overdue",IF(C2=0,"Pending","Paid"))
A3: 46082 | B3: Emma Wilson | C3: 80 | D3: Session | E3: =IF(TODAY()-A3>7,"Overdue",IF(C3=0,"Pending","Paid"))
A4: 46096 | B4: Sarah Miller | C4: 120 | D4: Session | E4: =IF(TODAY()-A4>7,"Overdue",IF(C4=0,"Pending","Paid"))
A5: 46109 | B5: Emma Wilson | C5: 80 | D5: Session | E5: =IF(TODAY()-A5>7,"Overdue",IF(C5=0,"Pending","Paid"))
E6: =IF(A6="","",IF(TODAY()-A6>7,"Overdue",IF(C6=0,"Pending","Paid")))
E7: =IF(A7="","",IF(TODAY()-A7>7,"Overdue",IF(C7=0,"Pending","Paid")))
E8: =IF(A8="","",IF(TODAY()-A8>7,"Overdue",IF(C8=0,"Pending","Paid")))
E9: =IF(A9="","",IF(TODAY()-A9>7,"Overdue",IF(C9=0,"Pending","Paid")))
E10: =IF(A10="","",IF(TODAY()-A10>7,"Overdue",IF(C10=0,"Pending","Paid")))
E11: =IF(A11="","",IF(TODAY()-A11>7,"Overdue",IF(C11=0,"Pending","Paid")))
E12: =IF(A12="","",IF(TODAY()-A12>7,"Overdue",IF(C12=0,"Pending","Paid")))
E13: =IF(A13="","",IF(TODAY()-A13>7,"Overdue",IF(C13=0,"Pending","Paid")))
E14: =IF(A14="","",IF(TODAY()-A14>7,"Overdue",IF(C14=0,"Pending","Paid")))
E15: =IF(A15="","",IF(TODAY()-A15>7,"Overdue",IF(C15=0,"Pending","Paid")))
E16: =IF(A16="","",IF(TODAY()-A16>7,"Overdue",IF(C16=0,"Pending","Paid")))
E17: =IF(A17="","",IF(TODAY()-A17>7,"Overdue",IF(C17=0,"Pending","Paid")))
... E65: =IF(A65="","",IF(TODAY()-A65>7,"Overdue",IF(C65=0,"Pending","Paid")))

Sheet Expenses
A1: Date | B1: Category | C1: Description | D1: Amount | E1: Tax
A2: 46086 | B2: Equipment | C2: Resistance bands | D2: 45 | E2: 8.55
A3: 46091 | B3: Marketing | C3: Instagram ads | D3: 30 | E3: 5.7
A4: 46096 | B4: Education | C4: Online course | D4: 89 | E4: 16.91
A5: 46101 | B5: Office | C5: Printer ink | D5: 28.5 | E5: 5.42
