Workbook

Sheet Start
C2: Ultimate Wedding Budget & Vendor Tracker
C3: Effortlessly manage your wedding budget and vendor details with this comprehensive Excel tracker. Stay organized and on track with real-time calculations and insightful KPIs.
C5: How it works
B6: 1. | C6: Enter your wedding budget in the 'Budget' sheet.
B7: 2. | C7: List all vendors and their details in the 'Vendors' sheet.
B8: 3. | C8: Track payments and deadlines in the 'Payments' sheet.
B9: 4. | C9: Use the 'Summary' sheet to view your overall budget status.
B10: 5. | C10: Monitor your KPIs on the 'Dashboard' sheet.
B11: 6. | C11: Adjust your budget and vendor details as needed.
B12: 7. | C12: Export your data for sharing with vendors or family.
C14: Only fill in white cells – green columns calculate automatically.
C16: Go to sheet
C17: → Dashboard
C18: → Budget
C19: → Vendors
C20: → Payments
C21: → Summary
C23: Made by Haiktec · haiktec.tech

Sheet Dashboard
B2: Dashboard – Ultimate Wedding Budget & Vendor Tracker
B4: Key figures
B5: Total Budget | C5: =SUM('Budget'!B2:B300)
B6: Total Spent | C6: =SUM('Payments'!C2:C300)
B7: Remaining Budget | C7: =SUM('Summary'!C2)
B8: Number of Vendors | C8: =COUNTA('Vendors'!A2:A300)
B9: Pending Payments | C9: =COUNTIF('Payments'!D2:D300,"Pending")

Sheet Budget
A1: Category | B1: Planned Amount | C1: Actual Amount | D1: Difference
A2: Venue | B2: 5000 | D2: =C2-B2
A3: Catering | B3: 3000 | D3: =C3-B3
A4: Photography | B4: 2000 | D4: =C4-B4
D5: =IF(A5="","",C5-B5)
D6: =IF(A6="","",C6-B6)
D7: =IF(A7="","",C7-B7)
D8: =IF(A8="","",C8-B8)
D9: =IF(A9="","",C9-B9)
D10: =IF(A10="","",C10-B10)
D11: =IF(A11="","",C11-B11)
D12: =IF(A12="","",C12-B12)
D13: =IF(A13="","",C13-B13)
D14: =IF(A14="","",C14-B14)
D15: =IF(A15="","",C15-B15)
D16: =IF(A16="","",C16-B16)
... D64: =IF(A64="","",C64-B64)

Sheet Vendors
A1: Vendor Name | B1: Service | C1: Contact | D1: Cost | E1: Paid | F1: Balance
A2: ABC Catering | B2: Catering | C2: john@abc.com | D2: 3000 | E2: 1500 | F2: =D2-E2
A3: XYZ Photography | B3: Photography | C3: jane@xyz.com | D3: 2000 | F3: =D3-E3
F4: =IF(A4="","",D4-E4)
F5: =IF(A5="","",D5-E5)
F6: =IF(A6="","",D6-E6)
F7: =IF(A7="","",D7-E7)
F8: =IF(A8="","",D8-E8)
F9: =IF(A9="","",D9-E9)
F10: =IF(A10="","",D10-E10)
F11: =IF(A11="","",D11-E11)
F12: =IF(A12="","",D12-E12)
F13: =IF(A13="","",D13-E13)
F14: =IF(A14="","",D14-E14)
F15: =IF(A15="","",D15-E15)
... F63: =IF(A63="","",D63-E63)

Sheet Payments
A1: Date | B1: Vendor | C1: Amount | D1: Status
A2: 46037 | B2: ABC Catering | C2: 1500 | D2: Paid
A3: 46054 | B3: XYZ Photography | C3: 1000 | D3: Pending

Sheet Summary
A1: Total Budget | B1: Total Spent | C1: Remaining
