Workbook

Sheet Start
C2: Ultimate Berlin & Potsdam Family Trip Budget Tracker
C3: Plan your perfect family trip to Berlin & Potsdam with this all-in-one budget tracker and itinerary planner. Stay organized and avoid overspending while making unforgettable memories.
C5: How it works
B6: 1. | C6: Enter your planned daily budget and activities
B7: 2. | C7: Log all trip expenses as you go
B8: 3. | C8: Compare actual vs. planned spending
B9: 4. | C9: Use the attraction rating system to prioritize visits
B10: 5. | C10: Review your daily itinerary each morning
B11: 6. | C11: Track transportation costs between locations
B12: 7. | C12: Save money with our family discount tips
C14: Only fill in white cells – green columns calculate automatically.
C16: Go to sheet
C17: → Dashboard
C18: → Daily Budget
C19: → Itinerary
C21: Made by Haiktec · haiktec.tech

Sheet Dashboard
B2: Dashboard – Ultimate Berlin & Potsdam Family Trip Budget Tracker
B4: Key figures
B5: Total Planned Budget | C5: =SUM('Daily Budget'!D2:D300)
B6: Total Actual Spending | C6: =SUM('Daily Budget'!E2:E300)
B7: Budget Variance | C7: =SUM('Daily Budget'!F2:F300)
B8: Top Expense Category | C8: =INDEX('Daily Budget'!B2:B300,MATCH(MAX('Daily Budget'!E2:E300),'Daily Budget'!E2:E300,0))
B9: Total Activities Planned | C9: =COUNTA('Itinerary'!C2:C300)
B10: Transportation Costs | C10: =SUMIF('Daily Budget'!B2:B300,"Transport",'Daily Budget'!E2:E300)

Sheet Daily Budget
A1: Date | B1: Category | C1: Activity | D1: Planned Cost | E1: Actual Cost | F1: Difference
A2: 46218 | B2: Attractions | C2: Pergamon Museum family tickets | D2: 32 | F2: =E2-D2
A3: 46218 | B3: Food | C3: Lunch at Alexanderplatz | D3: 45 | F3: =E3-D3
A4: 46218 | B4: Transport | C4: Tageskarte AB zones | D4: 21 | F4: =E4-D4
A5: 46219 | B5: Attractions | C5: Sanssouci Palace entry | D5: 28 | F5: =E5-D5
A6: 46219 | B6: Food | C6: Dinner in Potsdam | D6: 55 | F6: =E6-D6
A7: 46220 | B7: Attractions | C7: Berlin Zoo family tickets | D7: 45 | F7: =E7-D7
A8: 46220 | B8: Shopping | C8: Souvenirs | D8: 30 | F8: =E8-D8
A9: 46221 | B9: Transport | C9: Airport transfer | D9: 35 | F9: =E9-D9
F10: =IF(A10="","",E10-D10)
F11: =IF(A11="","",E11-D11)
F12: =IF(A12="","",E12-D12)
F13: =IF(A13="","",E13-D13)
F14: =IF(A14="","",E14-D14)
F15: =IF(A15="","",E15-D15)
F16: =IF(A16="","",E16-D16)
F17: =IF(A17="","",E17-D17)
F18: =IF(A18="","",E18-D18)
F19: =IF(A19="","",E19-D19)
F20: =IF(A20="","",E20-D20)
F21: =IF(A21="","",E21-D21)
... F89: =IF(A89="","",E89-D89)

Sheet Itinerary
A1: Date | B1: Time | C1: Activity | D1: Location | E1: Priority | F1: Notes
A2: 46218 | B2: 09:00-12:00 | C2: Pergamon Museum | D2: Museum Island | E2: High | F2: Book tickets in advance
A3: 46218 | B3: 12:30-14:00 | C3: Lunch at Alexanderplatz | D3: Alexanderplatz | E3: Medium
A4: 46218 | B4: 14:30-17:00 | C4: TV Tower visit | D4: Alexanderplatz | E4: Medium | F4: Check weather forecast
A5: 46219 | B5: 10:00-15:00 | C5: Potsdam day trip | D5: Sanssouci Palace | E5: High | F5: Pack picnic lunch
A6: 46219 | B6: 19:00-21:00 | C6: Dinner in Potsdam | D6: Dutch Quarter | E6: Medium
A7: 46220 | B7: 09:30-12:30 | C7: Berlin Zoo | D7: Tiergarten | E7: High | F7: Kids favorite
A8: 46220 | B8: 13:00-15:00 | C8: Shopping at KaDeWe | D8: Tauentzienstraße | E8: Low | F8: Toy department
A9: 46221 | B9: 08:00-10:00 | C9: Breakfast & packing | D9: Hotel | E9: High | F9: Check out by 11
