Workbook

Sheet Start
C2: Ultimate Berlin & Potsdam Travel Budget Planner & Itinerary Tracker for Women
C3: Plan your perfect Berlin & Potsdam getaway with this all-in-one travel planner. Track expenses, schedule activities and optimize your budget effortlessly.
C5: How it works
B6: 1. | C6: Set your total budget in the Budget sheet
B7: 2. | C7: Add expected expenses in categories
B8: 3. | C8: Plan daily activities in the Itinerary
B9: 4. | C9: Track actual expenses during your trip
B10: 5. | C10: Monitor budget usage on the Dashboard
C12: Only fill in white cells – green columns calculate automatically.
C14: Go to sheet
C15: → Dashboard
C16: → Budget
C17: → Itinerary
C18: → Expenses
C20: Made by Haiktec · haiktec.tech

Sheet Dashboard
B2: Dashboard – Ultimate Berlin & Potsdam Travel Budget Planner & Itinerary
B4: Key figures
B5: Total Budget | C5: =SUM(Budget!B2:B50)
B6: Total Spent | C6: =SUM(Expenses!D2:D100)
B7: Budget Remaining | C7: =KPI_1-KPI_2
B8: Days Until Trip | C8: =DATEDIF(TODAY(),MIN(Itinerary!A2:A100),"d")
B9: Most Expensive Activity | C9: =MAX(Itinerary!F2:F100)
B10: Activities Planned | C10: =COUNTA(Itinerary!C2:C100)

Sheet Budget
A1: Category | B1: Planned Amount | C1: Actual Amount | D1: Difference
A2: Accommodation | B2: 1500 | D2: =C2-B2
A3: Food & Drinks | B3: 800 | D3: =C3-B3
A4: Museum Entries | B4: 150 | D4: =C4-B4
A5: Public Transport | B5: 120 | D5: =C5-B5
A6: Shopping | B6: 300 | D6: =C6-B6
A7: Entertainment | B7: 200 | D7: =C7-B7
D8: =IF(A8="","",C8-B8)
D9: =IF(A9="","",C9-B9)
D10: =IF(A10="","",C10-B10)
D11: =IF(A11="","",C11-B11)
D12: =IF(A12="","",C12-B12)
D13: =IF(A13="","",C13-B13)
D14: =IF(A14="","",C14-B14)
D15: =IF(A15="","",C15-B15)
D16: =IF(A16="","",C16-B16)
D17: =IF(A17="","",C17-B17)
D18: =IF(A18="","",C18-B18)
D19: =IF(A19="","",C19-B19)
... D37: =IF(A37="","",C37-B37)

Sheet Itinerary
A1: Date | B1: Time | C1: Activity | D1: Location | E1: Reservation | F1: Cost
A2: 46188 | B2: 10:00 | C2: Check-in Hotel | D2: Hotel am Steinplatz | E2: Confirmed | F2: 0
A3: 46188 | B3: 13:00 | C3: Lunch | D3: KaDeWe Food Court | F3: 25
A4: 46188 | B4: 15:00 | C4: Pergamon Museum | D4: Museum Island | E4: Booked | F4: 14
A5: 46189 | B5: 09:30 | C5: Breakfast | D5: House of Small Wonder | F5: 15
A6: 46189 | B6: 11:00 | C6: Potsdam Day Trip | D6: Sanssouci Palace | F6: 30
A7: 46190 | B7: 14:00 | C7: Shopping | D7: Bikini Berlin | F7: 120
A8: 46190 | B8: 19:30 | C8: Dinner | D8: Nobelhart & Schmutzig | E8: Reserved | F8: 90

Sheet Expenses
A1: Date | B1: Category | C1: Item | D1: Amount | E1: Payment Method | F1: Notes
A2: 46188 | B2: Accommodation | C2: Hotel Deposit | D2: 450 | E2: Credit Card
A3: 46188 | B3: Food & Drinks | C3: Airport Coffee | D3: 4.5 | E3: Cash
A4: 46188 | B4: Transport | C4: Day Pass | D4: 9.5 | E4: Credit Card | F4: ABCDE Zone
A5: 46188 | B5: Food & Drinks | C5: Dinner | D5: 28 | E5: Cash | F5: Vietnamese
A6: 46189 | B6: Entertainment | C6: Club Entry | D6: 18 | E6: Cash | F6: Berghain
A7: 46189 | B7: Shopping | C7: Souvenirs | D7: 45 | E7: Credit Card | F7: Käthe Wohlfahrt
