Workbook

Sheet Start
C2: Ultimate Black Forest Travel Budget Planner & Expense Tracker for Families
C3: A comprehensive Excel solution to effortlessly plan and track all expenses for your perfect family vacation in the Black Forest, ensuring you stay on budget while making unforgettable memories.
C5: How it works
B6: 1. | C6: Set your total vacation budget
B7: 2. | C7: Track expenses by category as you travel
B8: 3. | C8: Monitor spending against your budget limits
B9: 4. | C9: Optimize remaining funds for activities
B10: 5. | C10: Analyze spending patterns for future trips
B11: 6. | C11: Keep all travel documents digitally organized
C13: Only fill in white cells – green columns calculate automatically.
C15: Go to sheet
C16: → Dashboard
C17: → Expense Tracker
C18: → Budget Planner
C20: Made by Haiktec · haiktec.tech

Sheet Dashboard
B2: Dashboard – Ultimate Black Forest Travel Budget Planner & Expense Tracke
B4: Key figures
B5: Total Budget | C5: =SUM('Budget Planner'!B2:B8)
B6: Total Spent | C6: =SUM('Expense Tracker'!D2:D300)
B7: Remaining Funds | C7: =SUM('Budget Planner'!D2:D8)
B8: Most Expensive Day | C8: =TEXT(INDEX('Expense Tracker'!A2:A300,MATCH(MAX(SUMIF('Expense Tracker'!A2:A300,'Expense Tracker'!A2:A300,'Expense Tracker'!D2:D300)),SUMIF('Expense Tracker'!A2:A300,'Expense Tracker'!A2:A300,'Expense Tracker'!D2:D300),0)),"yyyy-mm-dd")
B9: Top Expense Category | C9: =INDEX('Expense Tracker'!B2:B300,MODE(MATCH('Expense Tracker'!B2:B300,'Expense Tracker'!B2:B300,0)))
B10: Average Daily Spend | C10: =AVERAGE(SUMIF('Expense Tracker'!A2:A300,UNIQUE('Expense Tracker'!A2:A300),'Expense Tracker'!D2:D300))

Sheet Expense Tracker
A1: Date | B1: Category | C1: Description | D1: Amount (EUR) | E1: Payment Method
A2: 46188 | B2: Accommodation | C2: Hotel Feldberg | D2: 120 | E2: Credit Card
A3: 46189 | B3: Transport | C3: Train Triberg to Freiburg | D3: 24.5 | E3: Cash
A4: 46189 | B4: Food | C4: Lunch at Gutach | D4: 35.8 | E4: Debit Card
A5: 46190 | B5: Activities | C5: Titisee boat rental | D5: 40 | E5: Cash
A6: 46190 | B6: Souvenirs | C6: Cuckoo clock | D6: 89.9 | E6: Credit Card
A7: 46191 | B7: Transport | C7: Car rental extension | D7: 65 | E7: Credit Card
A8: 46191 | B8: Food | C8: Dinner at Hausach | D8: 48.6 | E8: Debit Card
A9: 46192 | B9: Activities | C9: Black Forest Open Air Museum | D9: 28 | E9: Cash

Sheet Budget Planner
A1: Category | B1: Planned | C1: Spent | D1: Remaining | E1: Status
A2: Accommodation | B2: 600 | C2: 120 | D2: =B2-C2 | E2: =IF(D2/B2<0.2,"Alert",IF(D2/B2<0.4,"Warning","On Track"))
A3: Transport | B3: 300 | C3: 89.5 | D3: =B3-C3 | E3: =IF(D3/B3<0.2,"Alert",IF(D3/B3<0.4,"Warning","On Track"))
A4: Food | B4: 350 | C4: 84.4 | D4: =B4-C4 | E4: =IF(D4/B4<0.2,"Alert",IF(D4/B4<0.4,"Warning","On Track"))
A5: Activities | B5: 250 | C5: 68 | D5: =B5-C5 | E5: =IF(D5/B5<0.2,"Alert",IF(D5/B5<0.4,"Warning","On Track"))
A6: Souvenirs | B6: 150 | C6: 89.9 | D6: =B6-C6 | E6: =IF(D6/B6<0.2,"Alert",IF(D6/B6<0.4,"Warning","On Track"))
A7: Emergency | B7: 200 | C7: 0 | D7: =B7-C7 | E7: =IF(D7/B7<0.2,"Alert",IF(D7/B7<0.4,"Warning","On Track"))
A8: Other | B8: 150 | C8: 0 | D8: =B8-C8 | E8: =IF(D8/B8<0.2,"Alert",IF(D8/B8<0.4,"Warning","On Track"))
D9: =IF(A9="","",B9-C9) | E9: =IF(A9="","",IF(D9/B9<0.2,"Alert",IF(D9/B9<0.4,"Warning","On Track")))
D10: =IF(A10="","",B10-C10) | E10: =IF(A10="","",IF(D10/B10<0.2,"Alert",IF(D10/B10<0.4,"Warning","On Track")))
D11: =IF(A11="","",B11-C11) | E11: =IF(A11="","",IF(D11/B11<0.2,"Alert",IF(D11/B11<0.4,"Warning","On Track")))
D12: =IF(A12="","",B12-C12) | E12: =IF(A12="","",IF(D12/B12<0.2,"Alert",IF(D12/B12<0.4,"Warning","On Track")))
D13: =IF(A13="","",B13-C13) | E13: =IF(A13="","",IF(D13/B13<0.2,"Alert",IF(D13/B13<0.4,"Warning","On Track")))
