Workbook

Sheet Start
C2: Wedding Vendor & Budget Comparison Tracker
C3: Compare vendors side-by-side and track deposits with automatic cost calculations. Save hours of spreadsheet work with this professional wedding planning tool.
C5: How it works
B6: 1. | C6: Enter your wedding date and total budget
B7: 2. | C7: Add vendors with contact details and services
B8: 3. | C8: Input quotes with deposit requirements
B9: 4. | C9: Rank vendors by price/quality/availability
B10: 5. | C10: Track payments with due date reminders
B11: 6. | C11: Monitor budget allocation automatically
B12: 7. | C12: Print final comparison for decision making
C14: Only fill in white cells – green columns calculate automatically.
C16: Go to sheet
C17: → Dashboard
C18: → Vendors
C19: → Payments
C21: Made by Haiktec · haiktec.tech

Sheet Dashboard
B2: Dashboard – Wedding Vendor & Budget Comparison Tracker
B4: Key figures
B5: Total Budget | C5: =SUM(Vendors!D2:D50)
B6: Total Deposits | C6: =SUM(Payments!C2:C60)
B7: Top Vendor Rating | C7: =MAX(Vendors!H2:H50)
B8: Pending Payments | C8: =COUNTIF(Payments!F2:F60,"Pending")
B9: Avg Service Cost | C9: =AVERAGE(Vendors!D2:D50)
B10: Days Until Wedding | C10: =DATEDIF(TODAY(),Vendors!A1,"d")

Sheet Vendors
A1: Vendor | B1: Service | C1: Contact | D1: Quote | E1: Deposit% | F1: Deposit | G1: Balance | H1: Rating | I1: Booked
A2: Rose Garden | B2: Venue | C2: 555-1234 | D2: 5000 | E2: 0.3 | F2: =D2*E2 | G2: =D2-F2 | H2: 4.8 | I2: =IF(H2>4.5,"Pending","Rejected")
A3: Luminous Photos | B3: Photography | C3: 555-9876 | D3: 3200 | E3: 0.25 | F3: =D3*E3 | G3: =D3-F3 | H3: 4.9 | I3: =IF(H3>4.5,"Pending","Rejected")
A4: Gourmet Delight | B4: Catering | C4: 555-4567 | D4: 4200 | E4: 0.2 | F4: =D4*E4 | G4: =D4-F4 | H4: 4.7 | I4: =IF(H4>4.5,"Pending","Rejected")
F5: =IF(A5="","",D5*E5) | G5: =IF(A5="","",D5-F5) | I5: =IF(A5="","",IF(H5>4.5,"Pending","Rejected"))
F6: =IF(A6="","",D6*E6) | G6: =IF(A6="","",D6-F6) | I6: =IF(A6="","",IF(H6>4.5,"Pending","Rejected"))
F7: =IF(A7="","",D7*E7) | G7: =IF(A7="","",D7-F7) | I7: =IF(A7="","",IF(H7>4.5,"Pending","Rejected"))
F8: =IF(A8="","",D8*E8) | G8: =IF(A8="","",D8-F8) | I8: =IF(A8="","",IF(H8>4.5,"Pending","Rejected"))
F9: =IF(A9="","",D9*E9) | G9: =IF(A9="","",D9-F9) | I9: =IF(A9="","",IF(H9>4.5,"Pending","Rejected"))
F10: =IF(A10="","",D10*E10) | G10: =IF(A10="","",D10-F10) | I10: =IF(A10="","",IF(H10>4.5,"Pending","Rejected"))
F11: =IF(A11="","",D11*E11) | G11: =IF(A11="","",D11-F11) | I11: =IF(A11="","",IF(H11>4.5,"Pending","Rejected"))
F12: =IF(A12="","",D12*E12) | G12: =IF(A12="","",D12-F12) | I12: =IF(A12="","",IF(H12>4.5,"Pending","Rejected"))
F13: =IF(A13="","",D13*E13) | G13: =IF(A13="","",D13-F13) | I13: =IF(A13="","",IF(H13>4.5,"Pending","Rejected"))
F14: =IF(A14="","",D14*E14) | G14: =IF(A14="","",D14-F14) | I14: =IF(A14="","",IF(H14>4.5,"Pending","Rejected"))
F15: =IF(A15="","",D15*E15) | G15: =IF(A15="","",D15-F15) | I15: =IF(A15="","",IF(H15>4.5,"Pending","Rejected"))
F16: =IF(A16="","",D16*E16) | G16: =IF(A16="","",D16-F16) | I16: =IF(A16="","",IF(H16>4.5,"Pending","Rejected"))
... F54: =IF(A54="","",D54*E54) | G54: =IF(A54="","",D54-F54) | I54: =IF(A54="","",IF(H54>4.5,"Pending","Rejected"))

Sheet Payments
A1: Date | B1: Vendor | C1: Amount | D1: Type | E1: Due Date | F1: Status
A2: 46082 | B2: Rose Garden | C2: 1500 | D2: Deposit | E2: 46096 | F2: =IF(E2<TODAY(),"Overdue","Pending")
A3: 46091 | B3: Gourmet Delight | C3: 840 | D3: Deposit | E3: 46082 | F3: =IF(E3<TODAY(),"Overdue","Pending")
F4: =IF(A4="","",IF(E4<TODAY(),"Overdue","Pending"))
F5: =IF(A5="","",IF(E5<TODAY(),"Overdue","Pending"))
F6: =IF(A6="","",IF(E6<TODAY(),"Overdue","Pending"))
F7: =IF(A7="","",IF(E7<TODAY(),"Overdue","Pending"))
F8: =IF(A8="","",IF(E8<TODAY(),"Overdue","Pending"))
F9: =IF(A9="","",IF(E9<TODAY(),"Overdue","Pending"))
F10: =IF(A10="","",IF(E10<TODAY(),"Overdue","Pending"))
F11: =IF(A11="","",IF(E11<TODAY(),"Overdue","Pending"))
F12: =IF(A12="","",IF(E12<TODAY(),"Overdue","Pending"))
F13: =IF(A13="","",IF(E13<TODAY(),"Overdue","Pending"))
F14: =IF(A14="","",IF(E14<TODAY(),"Overdue","Pending"))
F15: =IF(A15="","",IF(E15<TODAY(),"Overdue","Pending"))
... F63: =IF(A63="","",IF(E63<TODAY(),"Overdue","Pending"))
