Workbook

Sheet Inicio
C2: YouTube Content ROI Tracker & Budget Planner 2026
C3: Controla la rentabilidad de cada video y optimiza tu presupuesto de contenido con esta herramienta profesional para creadores.
C5: Cómo funciona
B6: 1. | C6: Planifica tu calendario mensual en la pestaña 'Contenido'
B7: 2. | C7: Registra métricas clave después de publicar cada video
B8: 3. | C8: Analiza el ROI por video en la pestaña 'Rendimiento'
B9: 4. | C9: Ajusta tu estrategia basada en los datos
B10: 5. | C10: Controla tus gastos en la pestaña 'Presupuesto'
B11: 6. | C11: Revisa el dashboard para insights clave
C13: Rellene solo las celdas blancas: las columnas verdes se calculan solas.
C15: Ir a la hoja
C16: → Resumen
C17: → Contenido
C18: → Rendimiento
C19: → Presupuesto
C21: Creado por Haiktec · haiktec.tech

Sheet Resumen
B2: Resumen – YouTube Content ROI Tracker & Budget Planner 2026
B4: Indicadores
B5: Ingresos totales | C5: =SUM(Rendimiento!E2:E100)
B6: Promedio tiempo de visionado | C6: =AVERAGE(Rendimiento!D2:D100)
B7: Videos publicados | C7: =COUNTIF(Contenido!E2:E100,'Publicado')
B8: Gasto total equipos | C8: =SUMIF(Presupuesto!C2:C100,'Equipo',Presupuesto!F2:F100)
B9: ROI promedio | C9: =AVERAGE(Rendimiento!F2:F100)
B10: Visitas totales | C10: =SUM(Rendimiento!C2:C100)

Sheet Contenido
A1: Fecha | B1: Tipo | C1: Título | D1: Duración (min) | E1: Estado | F1: URL
A2: 46082 | B2: Tutorial | C2: Cómo optimizar miniaturas | D2: 12 | E2: Publicado
A3: 46089 | B3: Review | C3: Nueva cámara 2026 | D3: 15 | E3: Grabando
A4: 46096 | B4: Vlog | C4: Detrás de escenas | D4: 8 | E4: Editando
A5: 46103 | B5: Tutorial | C5: Edición avanzada | D5: 18 | E5: Planificado

Sheet Rendimiento
A1: Fecha | B1: Título | C1: Visitas | D1: Tiempo (min) | E1: Ingresos | F1: ROI
A2: 46054 | B2: Guía SEO YouTube | C2: 12500 | D2: 32500 | E2: 58.3 | F2: =E2/20*100
A3: 46061 | B3: Mejor micrófono 2026 | C3: 8700 | D3: 21000 | E3: 42.15 | F3: =E3/20*100
A4: 46068 | B4: Setup estudio pequeño | C4: 14300 | D4: 40100 | E4: 72.8 | F4: =E4/20*100
A5: 46075 | B5: Trucos iluminación | C5: 9600 | D5: 24500 | E5: 51.2 | F5: =E5/20*100
F6: =IF(A6="","",E6/20*100)
F7: =IF(A7="","",E7/20*100)
F8: =IF(A8="","",E8/20*100)
F9: =IF(A9="","",E9/20*100)
F10: =IF(A10="","",E10/20*100)
F11: =IF(A11="","",E11/20*100)
F12: =IF(A12="","",E12/20*100)
F13: =IF(A13="","",E13/20*100)
F14: =IF(A14="","",E14/20*100)
F15: =IF(A15="","",E15/20*100)
F16: =IF(A16="","",E16/20*100)
F17: =IF(A17="","",E17/20*100)
... F35: =IF(A35="","",E35/20*100)

Sheet Presupuesto
A1: Fecha | B1: Concepto | C1: Categoría | D1: Cantidad | E1: Precio | F1: Total
A2: 46082 | B2: SD Card 128GB | C2: Equipo | D2: 2 | E2: 29.99 | F2: =D2*E2
A3: 46086 | B3: Suscripción Adobe | C3: Software | D3: 1 | E3: 22.99 | F3: =D3*E3
A4: 46093 | B4: Viaje locación | C4: Producción | D4: 1 | E4: 85 | F4: =D4*E4
A5: 46101 | B5: Microfondo verde | C5: Equipo | D5: 1 | E5: 45.5 | F5: =D5*E5
F6: =IF(A6="","",D6*E6)
F7: =IF(A7="","",D7*E7)
F8: =IF(A8="","",D8*E8)
F9: =IF(A9="","",D9*E9)
F10: =IF(A10="","",D10*E10)
F11: =IF(A11="","",D11*E11)
F12: =IF(A12="","",D12*E12)
F13: =IF(A13="","",D13*E13)
F14: =IF(A14="","",D14*E14)
F15: =IF(A15="","",D15*E15)
F16: =IF(A16="","",D16*E16)
F17: =IF(A17="","",D17*E17)
... F35: =IF(A35="","",D35*E35)
