Workbook

Sheet Start
C2: YouTube Analytics & Content ROI Tracker - Creator Pro Edition
C3: Track video performance, ad revenue, and content investment ROI in one place. Optimize your YouTube strategy with data-driven insights.
C5: How it works
B6: 1. | C6: Enter basic video details (title, publish date, length)
B7: 2. | C7: Add production costs (equipment, editing, etc.)
B8: 3. | C8: Input monthly performance metrics
B9: 4. | C9: Track sponsorship details if applicable
B10: 5. | C10: Review ROI calculations
B11: 6. | C11: Use filters to compare content types
B12: 7. | C12: Check dashboard KPIs monthly
C14: Only fill in white cells – green columns calculate automatically.
C16: Go to sheet
C17: → Dashboard
C18: → Video Performance
C19: → Financials
C20: → Dashboard-2
C22: Made by Haiktec · haiktec.tech

Sheet Dashboard
B2: Dashboard – YouTube Analytics & Content ROI Tracker - Creator Pro Editio
B4: Key figures
B5: Total Views | C5: =SUM('Video Performance'!E2:E300)
B6: Avg Watch Time | C6: =AVERAGE('Video Performance'!F2:F300)
B7: Total Revenue | C7: =SUM('Financials'!C2:D300)
B8: Avg ROI | C8: =AVERAGE('Financials'!G2:G300)
B9: Top Performing Video | C9: =INDEX('Video Performance'!B2:B300,MATCH(MAX('Video Performance'!E2:E300),'Video Performance'!E2:E300,0))
B10: Sponsorship Income | C10: =SUM('Financials'!D2:D300)

Sheet Video Performance
A1: Publish Date | B1: Video Title | C1: Video Length | D1: Category | E1: Views | F1: Watch Time | G1: Likes | H1: Comments
A2: 46027 | B2: How to Edit Faster in Premiere Pro | C2: 0.5 | D2: Tutorial | E2: 15234 | F2: 4231 | G2: 524 | H2: 87
A3: 46034 | B3: My $10,000 Studio Setup | C3: 0.75 | D3: Gear | E3: 28901 | F3: 11234 | G3: 1203 | H3: 243
A4: 46041 | B4: January Income Report | C4: 1.25 | D4: Vlog | E4: 8701 | F4: 3245 | G4: 389 | H4: 45

Sheet Financials
A1: Video Title | B1: Production Cost | C1: Ad Revenue | D1: Sponsorship | E1: Expenses | F1: Net Profit | G1: ROI
A2: How to Edit Faster in Premiere Pro | B2: 85 | C2: 143.25 | D2: 0 | E2: 12.5 | F2: =C2+D2-B2-E2 | G2: =F2/B2
A3: My $10,000 Studio Setup | B3: 120.5 | C3: 287.9 | D3: 300 | E3: 0 | F3: =C3+D3-B3-E3 | G3: =F3/B3
A4: January Income Report | B4: 65 | C4: 98.75 | D4: 0 | E4: 0 | F4: =C4+D4-B4-E4 | G4: =F4/B4
F5: =IF(A5="","",C5+D5-B5-E5) | G5: =IF(A5="","",F5/B5)
F6: =IF(A6="","",C6+D6-B6-E6) | G6: =IF(A6="","",F6/B6)
F7: =IF(A7="","",C7+D7-B7-E7) | G7: =IF(A7="","",F7/B7)
F8: =IF(A8="","",C8+D8-B8-E8) | G8: =IF(A8="","",F8/B8)
F9: =IF(A9="","",C9+D9-B9-E9) | G9: =IF(A9="","",F9/B9)
F10: =IF(A10="","",C10+D10-B10-E10) | G10: =IF(A10="","",F10/B10)
F11: =IF(A11="","",C11+D11-B11-E11) | G11: =IF(A11="","",F11/B11)
F12: =IF(A12="","",C12+D12-B12-E12) | G12: =IF(A12="","",F12/B12)
F13: =IF(A13="","",C13+D13-B13-E13) | G13: =IF(A13="","",F13/B13)
F14: =IF(A14="","",C14+D14-B14-E14) | G14: =IF(A14="","",F14/B14)
F15: =IF(A15="","",C15+D15-B15-E15) | G15: =IF(A15="","",F15/B15)
F16: =IF(A16="","",C16+D16-B16-E16) | G16: =IF(A16="","",F16/B16)
... F64: =IF(A64="","",C64+D64-B64-E64) | G64: =IF(A64="","",F64/B64)

Sheet Dashboard-2
A1: Metric | B1: Value | C1: Trend
