Workbook

Sheet Accueil
C2: YouTube Content ROI Tracker & Budget Planner 2026
C3: Maximisez votre retour sur investissement YouTube avec ce tracker complet qui analyse vos dépenses et revenus par vidéo. Optimisez votre budget contenu en visualisant ce qui performe réellement.
C5: Mode d'emploi
B6: 1. | C6: Configurez vos paramètres initiaux
B7: 2. | C7: Saisissez vos coûts par vidéo
B8: 3. | C8: Ajoutez vos revenus
B9: 4. | C9: Analysez les tendances
B10: 5. | C10: Identifiez les opportunités d'optimisation
B11: 6. | C11: Ajustez votre stratégie de contenu
C13: Remplissez uniquement les cellules blanches – les colonnes vertes se calculent seules.
C15: Aller à la feuille
C16: → Tableau de bord
C17: → Dépenses
C18: → Revenus
C19: → ROI
C21: Créé par Haiktec · haiktec.tech

Sheet Tableau de bord
B2: Tableau de bord – YouTube Content ROI Tracker & Budget Planner 2026
B4: Indicateurs
B5: Total dépenses | C5: =SUM('Dépenses'!D2:D300)
B6: Total revenus | C6: =SUM('Revenus'!C2:C300)
B7: ROI moyen | C7: =AVERAGE('ROI'!D2:D100)
B8: Vidéos suivies | C8: =COUNTA('ROI'!A2:A100)
B9: Meilleur ROI | C9: =MAX('ROI'!D2:D100)

Sheet Dépenses
A1: Date | B1: Type | C1: Description | D1: Montant | E1: Vidéo associée
A2: 46027 | B2: Matériel | C2: Microphone | D2: 249.99 | E2: Tuto débutants
A3: 46034 | B3: Logiciel | C3: Abonnement éditeur | D3: 19.99 | E3: Tous
A4: 46040 | B4: Musique | C4: Licence titre | D4: 49.5 | E4: Vlog vacances
A5: 46047 | B5: Publicité | C5: Campagne promo | D5: 150 | E5: Nouveau format

Sheet Revenus
A1: Date | B1: Source | C1: Montant | D1: Vidéo associée
A2: 46042 | B2: Publicités | C2: 87.25 | D2: Tuto débutants
A3: 46044 | B3: Partenariat | C3: 250 | D3: Test produit
A4: 46050 | B4: Dons | C4: 35.5 | D4: Vlog vacances
A5: 46052 | B5: Publicités | C5: 132.75 | D5: Nouveau format

Sheet ROI
A1: Vidéo | B1: Coûts | C1: Revenus | D1: ROI | E1: Durée
A2: Tuto débutants | B2: 269.98 | C2: 87.25 | D2: =(C2-B2)/B2 | E2: 1.5
A3: Test produit | B3: 89.5 | C3: 250 | D3: =(C3-B3)/B3 | E3: 2
A4: Vlog vacances | B4: 99.5 | C4: 35.5 | D4: =(C4-B4)/B4 | E4: 3
D5: =IF(A5="","",(C5-B5)/B5)
D6: =IF(A6="","",(C6-B6)/B6)
D7: =IF(A7="","",(C7-B7)/B7)
D8: =IF(A8="","",(C8-B8)/B8)
D9: =IF(A9="","",(C9-B9)/B9)
D10: =IF(A10="","",(C10-B10)/B10)
D11: =IF(A11="","",(C11-B11)/B11)
D12: =IF(A12="","",(C12-B12)/B12)
D13: =IF(A13="","",(C13-B13)/B13)
D14: =IF(A14="","",(C14-B14)/B14)
D15: =IF(A15="","",(C15-B15)/B15)
D16: =IF(A16="","",(C16-B16)/B16)
... D44: =IF(A44="","",(C44-B44)/B44)
