Workbook

Sheet 开始
C2: YouTube广告收入与成本追踪器
C3: 专业追踪您的YouTube广告收入和视频制作成本，优化您的盈利策略。
C5: 使用说明
B6: 1. | C6: 在'视频数据'表中输入每个视频的基本信息
B7: 2. | C7: 在'收入'表中记录广告收入和播放量
B8: 3. | C8: 在'支出'表中记录视频制作成本
B9: 4. | C9: 查看'仪表板'自动计算的关键指标
B10: 5. | C10: 根据数据分析优化内容策略
C12: 只需填写白色单元格，绿色列会自动计算。
C14: 打开工作表
C15: → 总览
C16: → 视频数据
C17: → 收入
C18: → 支出
C20: 由 Haiktec 制作 · haiktec.tech

Sheet 总览
B2: 总览 – YouTube广告收入与成本追踪器
B4: 关键指标
B5: 总收入 | C5: =SUM('收入'!D2:D300)
B6: 总支出 | C6: =SUM('支出'!D2:D300)
B7: 净收入 | C7: =SUM('收入'!D2:D300)-SUM('支出'!D2:D300)
B8: 平均千次收益 | C8: =AVERAGE('收入'!E2:E300)
B9: 视频总数 | C9: =COUNTA('视频数据'!A2:A300)

Sheet 视频数据
A1: 视频ID | B1: 发布日期 | C1: 标题 | D1: 长度(分) | E1: 类别
A2: vid001 | B2: 46096 | C2: 春季花园入门 | D2: 12 | E2: 园艺
A3: vid002 | B3: 46103 | C3: 家庭健身5分钟 | D3: 5 | E3: 健康

Sheet 收入
A1: 视频ID | B1: 日期 | C1: 播放次数 | D1: 广告收入(€) | E1: 千次播放收益
A2: vid001 | B2: 46097 | C2: 1250 | D2: 5.48 | E2: =D2/(C2/1000)
A3: vid001 | B3: 46098 | C3: 1870 | D3: 8.23 | E3: =D3/(C3/1000)
E4: =IF(A4="","",D4/(C4/1000))
E5: =IF(A5="","",D5/(C5/1000))
E6: =IF(A6="","",D6/(C6/1000))
E7: =IF(A7="","",D7/(C7/1000))
E8: =IF(A8="","",D8/(C8/1000))
E9: =IF(A9="","",D9/(C9/1000))
E10: =IF(A10="","",D10/(C10/1000))
E11: =IF(A11="","",D11/(C11/1000))
E12: =IF(A12="","",D12/(C12/1000))
E13: =IF(A13="","",D13/(C13/1000))
E14: =IF(A14="","",D14/(C14/1000))
E15: =IF(A15="","",D15/(C15/1000))
... E103: =IF(A103="","",D103/(C103/1000))

Sheet 支出
A1: 视频ID | B1: 日期 | C1: 类别 | D1: 金额(€) | E1: 付款方式
A2: vid001 | B2: 46091 | C2: 设备 | D2: 89.9 | E2: 信用卡
A3: vid001 | B3: 46092 | C3: 音乐授权 | D3: 15 | E3: PayPal
